bibliometa_vis/__init__.py
bibliometa_vis/config.py
bibliometa_vis/visualization.py
bibliometa_vis-0.1.1.dist-info/LICENSE
bibliometa_vis-0.1.1.dist-info/WHEEL
bibliometa_vis-0.1.1.dist-info/METADATA
bibliometa_vis-0.1.1.dist-info/RECORD
