Metadata-Version: 2.1
Name: bibliometa-vis
Version: 0.1.1
Summary: An extension package for Bibliometa that provides visualization functions
Home-page: https://bibliometa-vis.readthedocs.io
License: MIT
Author: Andreas Lüschow
Author-email: lueschow@sub.uni-goettingen.de
Requires-Python: >=3.8,<3.10
Classifier: License :: OSI Approved :: MIT License
Classifier: Programming Language :: Python :: 3
Classifier: Programming Language :: Python :: 3.8
Requires-Dist: bibliometa (>=0.1.3,<0.2.0)
Requires-Dist: cartopy (>=0.20.0,<0.21.0)
Requires-Dist: cython (>=0.29.24,<0.30.0)
Requires-Dist: geopandas (>=0.9.0,<0.10.0)
Requires-Dist: loguru (>=0.5.3,<0.6.0)
Requires-Dist: matplotlib (>=3.4.3,<4.0.0)
Requires-Dist: networkx (>=2.6.2,<3.0.0)
Requires-Dist: shapely (>=1.7.1,<2.0.0)
Project-URL: Repository, https://github.com/alueschow/bibliometa-vis
